{
    "nodes": [
      {"id": "Tim", "group": 1, "gender": 0},
      {"id": "Neza", "group": 1, "gender": 1},
      {"id": "Kata", "group": 1, "gender": 1},
      {"id": "Talha", "group": 1, "gender": 0},
      {"id": "Victoria", "group": 1, "gender": 1},
      {"id": "Ruxi", "group": 1, "gender": 1},
      {"id": "Ariel", "group": 1, "gender": 0},
      {"id": "Dani", "group": 1, "gender": 1},
      {"id": "Kalle", "group": 1, "gender": 0},
      {"id": "Jesse", "group": 1, "gender": 0},
      {"id": "Erik", "group": 2, "gender": 0},
      {"id": "Simo", "group": 2, "gender": 0},
      {"id": "Maria", "group": 3, "gender": 1},
      {"id": "Susanna", "group": 2, "gender": 1},
      {"id": "Sarah", "group": 2, "gender": 1},
      {"id": "Elena", "group": 2, "gender": 1},
      {"id": "Thomas", "group": 3, "gender": 0},
      {"id": "Alexander", "group": 3, "gender": 0},
      {"id": "Julia", "group": 3, "gender": 1},
      {"id": "Ben", "group": 3, "gender": 0},
      {"id": "Martin", "group": 3, "gender": 0},
      {"id": "Viola", "group": 3, "gender": 1},
      {"id": "Cecilia", "group": 3, "gender": 1},
      {"id": "Emma", "group": 3, "gender": 1},
      {"id": "Rebecca", "group": 4, "gender": 1},
      {"id": "Joanna", "group": 4, "gender": 1},
      {"id": "Ross", "group": 5, "gender": 0},
      {"id": "John", "group": 4, "gender": 0}
    ],
    "links": [
      {"source": "Neza", "target": "Ruxi", "value": 1},
      {"source": "Neza", "target": "Kata", "value": 2},
      {"source": "Neza", "target": "Victoria", "value": 3},
      {"source": "Tim", "target": "Ruxi", "value": 3},
      {"source": "Tim", "target": "Ariel", "value": 1},
      {"source": "Tim", "target": "Kata", "value": 1},
      {"source": "Talha", "target": "Victoria", "value": 1},
      {"source": "Talha", "target": "Ariel", "value": 1},
      {"source": "Talha", "target": "Kata", "value": 2},
      {"source": "Victoria", "target": "Neza", "value": 1},
      {"source": "Victoria", "target": "Ruxi", "value": 1},
      {"source": "Victoria", "target": "Talha", "value": 3},
      {"source": "Ariel", "target": "Kata", "value": 3},
      {"source": "Ariel", "target": "Ruxi", "value": 5},
      {"source": "Ariel", "target": "Tim", "value": 1},
      {"source": "Ruxi", "target": "Kata", "value": 1},
      {"source": "Ruxi", "target": "Neza", "value": 1},
      {"source": "Ruxi", "target": "Tim", "value": 1},
      {"source": "Kata", "target": "Ruxi", "value": 4},
      {"source": "Kata", "target": "Victoria", "value": 4},
      {"source": "Kata", "target": "Neza", "value": 4},
      {"source": "Ben", "target": "Thomas", "value": 4},
      {"source": "Ben", "target": "Alexander", "value": 4},
      {"source": "Ben", "target": "Julia", "value": 4},
      {"source": "Martin", "target": "Thomas", "value": 3},
      {"source": "Martin", "target": "Alexander", "value": 3},
      {"source": "Martin", "target": "Julia", "value": 3},
      {"source": "Martin", "target": "Ben", "value": 4},
      {"source": "Viola", "target": "Thomas", "value": 3},
      {"source": "Viola", "target": "Alexander", "value": 3},
      {"source": "Viola", "target": "Susanna", "value": 3},
      {"source": "Viola", "target": "Ben", "value": 3},
      {"source": "Viola", "target": "Kalle", "value": 5},
      {"source": "Cecilia", "target": "Thomas", "value": 3},
      {"source": "Cecilia", "target": "Alexander", "value": 3},
      {"source": "Cecilia", "target": "Julia", "value": 3},
      {"source": "Cecilia", "target": "Ben", "value": 3},
      {"source": "Cecilia", "target": "Kalle", "value": 4},
      {"source": "Cecilia", "target": "Viola", "value": 4},
      {"source": "Emma", "target": "Thomas", "value": 3},
      {"source": "Emma", "target": "Alexander", "value": 3},
      {"source": "Maria", "target": "Julia", "value": 3},
      {"source": "Emma", "target": "Ben", "value": 3},
      {"source": "Emma", "target": "Martin", "value": 4},
      {"source": "Emma", "target": "Simo", "value": 4},
      {"source": "Emma", "target": "Cecilia", "value": 4},
      {"source": "Rebecca", "target": "Maria", "value": 2},
      {"source": "Rebecca", "target": "Viola", "value": 5},
      {"source": "Joanna", "target": "Rebecca", "value": 5},
      {"source": "Joanna", "target": "Emma", "value": 1},
      {"source": "Joanna", "target": "Viola", "value": 2},
      {"source": "Ross", "target": "Erik", "value": 4},
      {"source": "Ross", "target": "Susanna", "value": 1},
      {"source": "Ross", "target": "Joanna", "value": 1},
      {"source": "John", "target": "Emma", "value": 5},
      {"source": "Erik", "target": "Ross", "value": 5},
      {"source": "John", "target": "Jesse", "value": 1},
      {"source": "John", "target": "Erik", "value": 1},
      {"source": "Dani", "target": "Viola", "value": 3},
      {"source": "Dani", "target": "John", "value": 3},
      {"source": "Dani", "target": "Sarah", "value": 2},
      {"source": "Thomas", "target": "John", "value": 2},
      {"source": "Thomas", "target": "Dani", "value": 2},
      {"source": "Susanna", "target": "Viola", "value": 2},
      {"source": "Thomas", "target": "Sarah", "value": 1},
      {"source": "Elena", "target": "Sarah", "value": 2},
      {"source": "Alexander", "target": "Dani", "value": 2},
      {"source": "Alexander", "target": "Susanna", "value": 2},
      {"source": "Alexander", "target": "Viola", "value": 2},
      {"source": "Alexander", "target": "Elena", "value": 1}
  
    ]
  }